validdict/__init__.py
validdict/contextual.py
validdict/helpers.py
validdict/key.py
validdict/locator.py
validdict/map.py
validdict/results.py
validdict/scalars.py
validdict/schema.py
validdict/seq.py
validdict/validator.py
validdict-0.1.1.dist-info/LICENSE
validdict-0.1.1.dist-info/METADATA
validdict-0.1.1.dist-info/WHEEL
validdict-0.1.1.dist-info/RECORD
