Metadata-Version: 2.1
Name: validdict
Version: 0.1.1
Summary: ValidDictorian: Declarative Python Dictionary Validator
License: MIT
Author: Scott Perry
Author-email: sperry04@users.noreply.github.com
Requires-Python: >=3.9,<4.0
Classifier: License :: OSI Approved :: MIT License
Classifier: Programming Language :: Python :: 3
Classifier: Programming Language :: Python :: 3.9
Classifier: Programming Language :: Python :: 3.10
Classifier: Programming Language :: Python :: 3.11
Classifier: Programming Language :: Python :: 3.12
